dwave/embedding/__init__.py
dwave/embedding/chain_breaks.py
dwave/embedding/chain_strength.py
dwave/embedding/chimera.py
dwave/embedding/diagnostic.py
dwave/embedding/drawing.py
dwave/embedding/exceptions.py
dwave/embedding/pegasus.py
dwave/embedding/polynomialembedder.py
dwave/embedding/transforms.py
dwave/embedding/utils.py
dwave/embedding/zephyr.py
dwave/system/__init__.py
dwave/system/coupling_groups.py
dwave/system/exceptions.py
dwave/system/flux_bias_offsets.py
dwave/system/package_info.py
dwave/system/schedules.py
dwave/system/temperatures.py
dwave/system/testing.py
dwave/system/utilities.py
dwave/system/warnings.py
dwave/system/composites/__init__.py
dwave/system/composites/cutoffcomposite.py
dwave/system/composites/embedding.py
dwave/system/composites/linear_ancilla.py
dwave/system/composites/parallel_embeddings.py
dwave/system/composites/reversecomposite.py
dwave/system/composites/tiling.py
dwave/system/composites/virtual_graph.py
dwave/system/samplers/__init__.py
dwave/system/samplers/clique.py
dwave/system/samplers/dwave_sampler.py
dwave/system/samplers/leap_hybrid_sampler.py
dwave_system-1.32.0.dist-info/licenses/LICENSE
dwave_system-1.32.0.dist-info/METADATA
dwave_system-1.32.0.dist-info/WHEEL
dwave_system-1.32.0.dist-info/top_level.txt
dwave_system-1.32.0.dist-info/RECORD
