Metadata-Version: 2.4
Name: dwave-system
Version: 1.32.0
Summary: All things D-Wave System.
Home-page: https://github.com/dwavesystems/dwave-system
Author: D-Wave Systems Inc.
Author-email: tools@dwavesys.com
License: Apache 2.0
Classifier: License :: OSI Approved :: Apache Software License
Classifier: Operating System :: OS Independent
Classifier: Development Status :: 3 - Alpha
Classifier: Programming Language :: Python :: 3 :: Only
Classifier: Programming Language :: Python :: 3.9
Classifier: Programming Language :: Python :: 3.10
Classifier: Programming Language :: Python :: 3.11
Classifier: Programming Language :: Python :: 3.12
Classifier: Programming Language :: Python :: 3.13
Requires-Python: >=3.9
License-File: LICENSE
Requires-Dist: dimod<0.14.0,>=0.12.20
Requires-Dist: dwave-optimization<0.8,>=0.1.0
Requires-Dist: dwave-cloud-client<0.14.0,>=0.12.0
Requires-Dist: dwave-networkx>=0.8.10
Requires-Dist: dwave-preprocessing>=0.5.0
Requires-Dist: homebase<2.0.0,>=1.0.0
Requires-Dist: minorminer<0.3.0,>=0.2.19
Requires-Dist: numpy>=1.21.6
Requires-Dist: dwave-samplers>=1.0.0
Requires-Dist: scipy>=1.7.3
Dynamic: author
Dynamic: author-email
Dynamic: classifier
Dynamic: description
Dynamic: home-page
Dynamic: license
Dynamic: license-file
Dynamic: requires-dist
Dynamic: requires-python
Dynamic: summary
